{
  "identifier": "cia-readingroom-document-cia-rdp82-00457r000300170001-3",
  "title": "CIA Reading Room cia-rdp82-00457r000300170001-3: POLITICAL INFORMATION: SOUTH CHINA DEMOCRATIC LEAGUE ANTI-AMERICAN ACTIVITY . HONGKONG",
  "date": "1947-01-28",
  "description": " 20X11 A ,,,DD 1300170001-3 ~~-...                                                    -- ---  ...E  .. COXF CEN                                        y 'ENT'R'-_-'' I `T LL. GIN'CE GROUP TEWL.,IGENCE REPORT COUNTRY  China SUBJECT  Political Information:  South China Democratic League Anti-American Activity, Hongkong 25X1A ORIGIN ,amy copy . 25X1C     6371 DIST. ' 28 January 1947 PAGES   1 SUPPLEMENT 25X1 C i'he> :=otiath China Headquarters of the liemocratio League,, with Hongkong as its Oise of oiler avions, has added its voice to the clamor for the withdrawal of ; aeri.can troops frrm,. Chi n.e.f.  On 24 November  191.;6 .. message or, this subject .; Cae Jed to the General Assembly of the United Nations? and released to !c:: two ha -i.is t lan;;uaL;e newspapers in Hongkong:,  The cable was signed by --t a (4.-     -,r'      ), head of the Canton branu~h of the Democratic F e., and Cfx'I.C C'-9>(   ..       )a in Charlie of the i,eaguecs propaganda in Hoackong. Orders for this anti-",
  "creator": "CIA Reading Room",
  "subject": "CIA Reading Room;",
  "collection": [
    "ciareadingroom",
    "usgovernmentmirrors",
    "government-documents"
  ],
  "txt_file": "cia-rdp82-00457r000300170001-3_djvu.txt",
  "txt_size": 2839,
  "pdf_url": "https://archive.org/download/cia-readingroom-document-cia-rdp82-00457r000300170001-3/cia-readingroom-document-cia-rdp82-00457r000300170001-3.pdf",
  "detail_url": "https://archive.org/details/cia-readingroom-document-cia-rdp82-00457r000300170001-3",
  "matched_term": "China Democratic League"
}