{
  "identifier": "cia-readingroom-document-cia-rdp80-00809a000700130238-2",
  "title": "CIA Reading Room cia-rdp80-00809a000700130238-2: SURVEY OF CHINA'S FOOD INDUSTRY, 1950",
  "date": "1953-09-14",
  "description": " Declassified in Part - Sanitized Copy Approved for Release 2012/02/08: CIA-RDP80-00809A000700130238-2 Cung-kuo_Kung-yeh, Neu Vol I, No 11, 1950. COUNTRY     China SUBJECT     Economic - Agriculture; food indtstry HOW PUBLISHED   Monthly periodical WHERE PUBLISHED   Shanghai DATE PUBLISHED   17 Mar 1950 LANGUAGE    Chinese Nil COW NANT CONT.... I.4.NATI0. arr[rn.. n. NATIONAL 1.71.11 or T.. 111ni .T. n. 117x11 T.t ?11-14 or .UICN.a All .. N... C.. NI AMP 11.4 Nl.o.1?  IT. n4t...PO. O. TON .nNunoN or m 10.71.71 ~. ANT NA..11 TO Al Y..Y7.oat.1 r.N... 11 .... .111711 NT LAW.  N1g011R1ON or la. FINN b r.o.Ia710. SURVEY OF CHINA'S FOOD INDUS7N'1  1950 1Comment and Summary:  The following report on the food indus- try of China gives information from an article by Li Chung-ying in the Shanghai monthly magazine Chung-kuo Kung-yeh (Chinese Industry). The author establishes the annual potential food supply per cap- ita in China as 481 catties of cereals.  He indicates that while rice and wheat a",
  "creator": "CIA Reading Room",
  "subject": "CIA Reading Room;",
  "collection": [
    "ciareadingroom",
    "usgovernmentmirrors",
    "government-documents"
  ],
  "txt_file": "cia-rdp80-00809a000700130238-2_djvu.txt",
  "txt_size": 35203,
  "pdf_url": "https://archive.org/download/cia-readingroom-document-cia-rdp80-00809a000700130238-2/cia-readingroom-document-cia-rdp80-00809a000700130238-2.pdf",
  "detail_url": "https://archive.org/details/cia-readingroom-document-cia-rdp80-00809a000700130238-2",
  "matched_term": "Shih Liang"
}